ipa_recognizer/__init__.py
ipa_recognizer/am.py
ipa_recognizer/audio.py
ipa_recognizer/decode.py
ipa_recognizer/feature.py
ipa_recognizer/recognizer.py
ipa_recognizer/run.py
ipa_recognizer-0.0.3.dist-info/METADATA
ipa_recognizer-0.0.3.dist-info/WHEEL
ipa_recognizer-0.0.3.dist-info/top_level.txt
ipa_recognizer-0.0.3.dist-info/RECORD
