Metadata-Version: 2.1
Name: ipa-recognizer
Version: 0.0.3
Summary: A pretrained IPA recognizer
Home-page: UNKNOWN
Author: Xinjian Li
Author-email: lixinjian1217@gmail.com
License: UNKNOWN
Platform: UNKNOWN
Requires-Dist: scikit-learn
Requires-Dist: numpy
Requires-Dist: scipy
Requires-Dist: webrtcvad
